{
   "brand": "HONDA",
   "models": [
      {
         "modelName": "HONDA Civic 5 Doors",
         "firstYearProduction": "1995",
         "engineType": "Gasoline, Diesel",
         "style": "Hatchback",
         "generations": [
            {
               "fullName": "HONDA Civic Hatchback",
               "firstYearProduction": "2021",
               "lastYearProduction": "Present",
               "drive type": "Front Wheel Drive",
               "gearBox": "6-speed manual",
               "length": "4549",
               "width": "1801",
               "height": "1415",
               "wheelBase": "2736",
               "wheelTrack": "1.547",
               "fuel": "Gasoline"
            },
            {
               "fullName": "HONDA Civic Hatchback",
               "firstYearProduction": "2019",
               "lastYearProduction": "2021",
               "drive type": "Front Wheel Drive",
               "gearBox": "6-Speed manual",
               "length": "4519",
               "width": "1798",
               "height": "1435",
               "wheelBase": "2700",
               "wheelTrack": "1547",
               "cargoVolume": "728",
               "fuel": "Gasoline"
            },
            {
               "fullName": "HONDA Civic 5 Doors",
               "firstYearProduction": "2016",
               "lastYearProduction": "2019",
               "topSpeed": "203",
               "acceleration": "10.9",
               "drive type": "Front Wheel Drive",
               "gearBox": "6-speed manual",
               "length": "4519",
               "width": "1798",
               "height": "1435",
               "wheelBase": "2700",
               "wheelTrack": "1.547",
               "cargoVolume": "479",
               "fuel": "Gasoline"
            },
            {
               "fullName": "HONDA Civic 5 Doors",
               "firstYearProduction": "2015",
               "lastYearProduction": "2016",
               "topSpeed": "187",
               "acceleration": "13",
               "drive type": "Front Wheel Drive",
               "gearBox": "6-speed manual",
               "length": "4369",
               "width": "1770",
               "height": "1590",
               "wheelBase": "2596",
               "wheelTrack": "1.539",
               "cargoVolume": "476",
               "fuel": "Gasoline"
            },
            {
               "fullName": "HONDA Civic 5 Doors",
               "firstYearProduction": "2012",
               "lastYearProduction": "2015",
               "topSpeed": "187",
               "acceleration": "13.4",
               "drive type": "Front Wheel Drive",
               "gearBox": "6-speed manual",
               "length": "4300",
               "width": "1770",
               "height": "1471",
               "wheelBase": "2596",
               "wheelTrack": "1.539",
               "cargoVolume": "476",
               "fuel": "Gasoline"
            },
            {
               "fullName": "HONDA Civic 5 Doors",
               "firstYearProduction": "2008",
               "lastYearProduction": "2011",
               "topSpeed": "177",
               "acceleration": "15",
               "drive type": "Front Wheel Drive",
               "gearBox": "6-speed automatic",
               "length": "4255",
               "width": "1755",
               "height": "1461",
               "wheelBase": "2634",
               "wheelTrack": "1.504",
               "cargoVolume": "484",
               "fuel": "Gasoline"
            },
            {
               "fullName": "HONDA Civic 5 Doors",
               "firstYearProduction": "2005",
               "lastYearProduction": "2008",
               "topSpeed": "171",
               "acceleration": "16.1",
               "drive type": "Front Wheel Drive",
               "gearBox": "6-speed automatic",
               "length": "4249",
               "width": "1760",
               "height": "1461",
               "wheelBase": "2639",
               "wheelTrack": "1.501",
               "cargoVolume": "484",
               "fuel": "Gasoline"
            },
            {
               "fullName": "HONDA Civic 5 Doors",
               "firstYearProduction": "2003",
               "lastYearProduction": "2005",
               "topSpeed": "175",
               "acceleration": "11.9",
               "drive type": "Front Wheel Drive",
               "gearBox": "5-Speed manual",
               "length": "4280",
               "width": "1699",
               "height": "1501",
               "wheelBase": "2680",
               "wheelTrack": "1.471",
               "cargoVolume": "368",
               "fuel": "Gasoline"
            },
            {
               "fullName": "HONDA Civic 5 Doors",
               "firstYearProduction": "2001",
               "lastYearProduction": "2003",
               "topSpeed": "175",
               "acceleration": "11.8",
               "drive type": "Front Wheel Drive",
               "gearBox": "5-Speed manual",
               "length": "4280",
               "width": "1699",
               "height": "1501",
               "wheelBase": "2680",
               "wheelTrack": "1.471",
               "cargoVolume": "368",
               "fuel": "Gasoline"
            },
            {
               "fullName": "HONDA Civic 5 Doors",
               "firstYearProduction": "1997",
               "lastYearProduction": "2001",
               "topSpeed": "176",
               "acceleration": "13.3",
               "drive type": "Front Wheel Drive",
               "gearBox": "5-Speed manual",
               "length": "4321",
               "width": "1699",
               "height": "1389",
               "wheelBase": "2619",
               "wheelTrack": "1.481",
               "cargoVolume": "379",
               "fuel": "Gasoline"
            },
            {
               "fullName": "HONDA Civic 5 Doors",
               "firstYearProduction": "1995",
               "lastYearProduction": "1997",
               "topSpeed": "172",
               "acceleration": "13.1",
               "drive type": "Front Wheel Drive",
               "gearBox": "5-Speed manual",
               "length": "4321",
               "width": "1699",
               "height": "1389",
               "wheelBase": "2619",
               "wheelTrack": "1.481",
               "fuel": "Gasoline"
            }
         ]
      },
      {
         "modelName": "HONDA HR-V 5 Doors",
         "firstYearProduction": "1999",
         "engineType": "Hybrid gasoline, Gasoline, Diesel",
         "style": "SUV (Sports Utility Vehicle)",
         "generations": [
            {
               "fullName": "HONDA HR-V",
               "firstYearProduction": "2021",
               "lastYearProduction": "Present",
               "drive type": "All Wheel Drive",
               "fuel": "Hybrid Gasoline"
            },
            {
               "fullName": "HONDA HR-V",
               "firstYearProduction": "2018",
               "lastYearProduction": "2021",
               "topSpeed": "192",
               "acceleration": "10.2",
               "drive type": "Front Wheel Drive",
               "gearBox": "6-speed manual",
               "length": "4333",
               "width": "1773",
               "height": "1605",
               "wheelBase": "2611",
               "wheelTrack": "1.534",
               "cargoVolume": "430",
               "fuel": "Gasoline"
            },
            {
               "fullName": "HONDA HR-V 5 doors",
               "firstYearProduction": "2014",
               "lastYearProduction": "2018",
               "topSpeed": "192",
               "acceleration": "10.2",
               "drive type": "Front Wheel Drive",
               "gearBox": "6-speed manual",
               "length": "4295",
               "width": "1773",
               "height": "1605",
               "wheelBase": "2611",
               "wheelTrack": "1.534",
               "cargoVolume": "688",
               "fuel": "Gasoline"
            },
            {
               "fullName": "HONDA HR-V 5 Doors",
               "firstYearProduction": "2001",
               "lastYearProduction": "2006",
               "topSpeed": "165",
               "acceleration": "11.7",
               "drive type": "Front Wheel Drive",
               "gearBox": "Manual, 5 Speed",
               "length": "4110",
               "width": "1699",
               "height": "1580",
               "wheelBase": "2451",
               "wheelTrack": "1.471",
               "cargoVolume": "283",
               "fuel": "Gasoline"
            },
            {
               "fullName": "HONDA HR-V 5 Doors",
               "firstYearProduction": "1999",
               "lastYearProduction": "2001",
               "topSpeed": "162",
               "acceleration": "12.1",
               "drive type": "Front Wheel Drive",
               "gearBox": "5-Speed manual",
               "length": "4110",
               "width": "1699",
               "height": "1590",
               "wheelBase": "2451",
               "wheelTrack": "1.471",
               "cargoVolume": "283",
               "fuel": "Gasoline"
            }
         ]
      },
      {
         "modelName": "HONDA Civic Sedan",
         "firstYearProduction": "1987",
         "engineType": "Gasoline, Natural gas, Hybrid",
         "generations": [
            {
               "fullName": "HONDA Civic Sedan",
               "firstYearProduction": "2021",
               "lastYearProduction": "Present",
               "drive type": "Front Wheel Drive",
               "gearBox": "CVT",
               "length": "4674",
               "width": "1801",
               "height": "1415",
               "wheelBase": "2736",
               "wheelTrack": "1.547",
               "cargoVolume": "408",
               "fuel": "Gasoline"
            },
            {
               "fullName": "HONDA Civic Sedan",
               "firstYearProduction": "2018",
               "lastYearProduction": "2021",
               "drive type": "Front Wheel Drive",
               "gearBox": "CVT",
               "length": "4630",
               "width": "1798",
               "height": "1415",
               "wheelBase": "2700",
               "wheelTrack": "1.547",
               "cargoVolume": "428",
               "fuel": "Gasoline"
            },
            {
               "fullName": "HONDA Civic Sedan",
               "firstYearProduction": "2016",
               "lastYearProduction": "2018",
               "drive type": "Front Wheel Drive",
               "gearBox": "CVT",
               "length": "4630",
               "width": "1798",
               "height": "1415",
               "wheelBase": "2700",
               "wheelTrack": "1.547",
               "cargoVolume": "428",
               "fuel": "Gasoline"
            },
            {
               "fullName": "HONDA Civic Sedan",
               "firstYearProduction": "2012",
               "lastYearProduction": "2016",
               "topSpeed": "200",
               "acceleration": "10.7",
               "drive type": "Front Wheel Drive",
               "gearBox": "5-speed automatic",
               "length": "4503",
               "width": "1753",
               "height": "1435",
               "wheelBase": "2670",
               "wheelTrack": "1.499",
               "cargoVolume": "354",
               "fuel": "Gasoline"
            },
            {
               "fullName": "HONDA Civic Sedan Si",
               "firstYearProduction": "2012",
               "lastYearProduction": "2016",
               "topSpeed": "201",
               "acceleration": "6.7",
               "drive type": "Front Wheel Drive",
               "gearBox": "6-speed manual",
               "length": "4503",
               "width": "1753",
               "height": "1435",
               "wheelBase": "2670",
               "wheelTrack": "1.499",
               "cargoVolume": "354",
               "fuel": "Gasoline"
            },
            {
               "fullName": "HONDA Civic Sedan HF",
               "firstYearProduction": "2012",
               "lastYearProduction": "2016",
               "topSpeed": "200",
               "acceleration": "10.7",
               "drive type": "Front Wheel Drive",
               "gearBox": "5-speed automatic",
               "length": "4503",
               "width": "1753",
               "height": "1435",
               "wheelBase": "2670",
               "wheelTrack": "1.499",
               "cargoVolume": "354",
               "fuel": "Gasoline"
            },
            {
               "fullName": "HONDA Civic Sedan Natural Gas",
               "firstYearProduction": "2012",
               "lastYearProduction": "2016",
               "drive type": "Front Wheel Drive",
               "gearBox": "5-speed automatic",
               "length": "4503",
               "width": "1753",
               "height": "1435",
               "wheelBase": "2670",
               "wheelTrack": "1.499",
               "cargoVolume": "354",
               "fuel": "Natural Gas"
            },
            {
               "fullName": "HONDA Civic Sedan",
               "firstYearProduction": "2008",
               "lastYearProduction": "2012",
               "topSpeed": "200",
               "acceleration": "9.1",
               "drive type": "Front Wheel Drive",
               "gearBox": "6-speed manual",
               "length": "4544",
               "width": "1750",
               "height": "1430",
               "wheelBase": "2703",
               "wheelTrack": "1.504",
               "cargoVolume": "391",
               "fuel": "Gasoline"
            },
            {
               "fullName": "HONDA Civic Sedan",
               "firstYearProduction": "2006",
               "lastYearProduction": "2008",
               "topSpeed": "192",
               "acceleration": "10.3",
               "drive type": "Front Wheel Drive",
               "gearBox": "5-speed automatic",
               "length": "4539",
               "width": "1750",
               "height": "1435",
               "wheelBase": "2703",
               "wheelTrack": "1.501",
               "cargoVolume": "385",
               "fuel": "Gasoline"
            },
            {
               "fullName": "HONDA Civic Sedan",
               "firstYearProduction": "2003",
               "lastYearProduction": "2005",
               "topSpeed": "177",
               "acceleration": "12.8",
               "drive type": "Front Wheel Drive",
               "gearBox": "5-Speed manual",
               "length": "4470",
               "width": "1694",
               "height": "1440",
               "wheelBase": "2619",
               "wheelTrack": "1.471",
               "cargoVolume": "450",
               "fuel": "Gasoline"
            },
            {
               "fullName": "HONDA Civic Sedan",
               "firstYearProduction": "2000",
               "lastYearProduction": "2003",
               "topSpeed": "170",
               "acceleration": "13.7",
               "drive type": "Front Wheel Drive",
               "gearBox": "4-speed automatic",
               "length": "4458",
               "width": "1715",
               "height": "1440",
               "wheelBase": "2619",
               "wheelTrack": "1.468",
               "cargoVolume": "447",
               "fuel": "Gasoline"
            },
            {
               "fullName": "HONDA Civic Sedan",
               "firstYearProduction": "1995",
               "lastYearProduction": "2000",
               "topSpeed": "182",
               "acceleration": "11",
               "drive type": "Front Wheel Drive",
               "gearBox": "5-Speed manual",
               "length": "4460",
               "width": "1699",
               "height": "1389",
               "wheelBase": "2619",
               "wheelTrack": "1.481",
               "fuel": "Gasoline"
            },
            {
               "fullName": "HONDA Civic Sedan",
               "firstYearProduction": "1991",
               "lastYearProduction": "1996",
               "topSpeed": "180",
               "acceleration": "9.7",
               "drive type": "Front Wheel Drive",
               "gearBox": "5-Speed manual",
               "length": "4399",
               "width": "1699",
               "height": "1379",
               "wheelBase": "2619",
               "wheelTrack": "1.481",
               "cargoVolume": "379",
               "fuel": "Gasoline"
            },
            {
               "fullName": "HONDA Civic Sedan",
               "firstYearProduction": "1987",
               "lastYearProduction": "1991",
               "topSpeed": "172",
               "acceleration": "9.8",
               "drive type": "Front Wheel Drive",
               "gearBox": "5-Speed manual",
               "length": "4229",
               "width": "1689",
               "height": "1359",
               "wheelBase": "2499",
               "wheelTrack": "1.450",
               "cargoVolume": "382",
               "fuel": "Gasoline"
            }
         ]
      },
      {
         "modelName": "HONDA Jazz / Fit",
         "firstYearProduction": "2002",
         "engineType": "Gasoline, Hybrid, Diesel",
         "style": "Hatchback",
         "generations": [
            {
               "fullName": "HONDA Jazz / Fit",
               "firstYearProduction": "2020",
               "lastYearProduction": "Present",
               "drive type": "Front Wheel Drive",
               "gearBox": "CVT",
               "length": "3995",
               "width": "1694",
               "height": "1539",
               "wheelBase": "2530",
               "wheelTrack": "1.486",
               "fuel": "Gasoline"
            },
            {
               "fullName": "HONDA Jazz / Fit",
               "firstYearProduction": "2017",
               "lastYearProduction": "2020",
               "topSpeed": "190",
               "acceleration": "11.2",
               "drive type": "Front Wheel Drive",
               "gearBox": "6-speed manual",
               "length": "4100",
               "width": "1702",
               "height": "1524",
               "wheelBase": "2530",
               "wheelTrack": "1.481",
               "cargoVolume": "470",
               "fuel": "Gasoline"
            },
            {
               "fullName": "HONDA Jazz/Fit",
               "firstYearProduction": "2013",
               "lastYearProduction": "2017",
               "topSpeed": "190",
               "acceleration": "11.2",
               "drive type": "Front Wheel Drive",
               "gearBox": "6-speed manual",
               "length": "4064",
               "width": "1702",
               "height": "1524",
               "wheelBase": "2530",
               "wheelTrack": "1.481",
               "cargoVolume": "470",
               "fuel": "Gasoline"
            },
            {
               "fullName": "HONDA Jazz/Fit",
               "firstYearProduction": "2008",
               "lastYearProduction": "2013",
               "topSpeed": "177",
               "acceleration": "12.5",
               "drive type": "Front Wheel Drive",
               "gearBox": "5-Speed manual",
               "length": "4105",
               "width": "1694",
               "height": "1524",
               "wheelBase": "2499",
               "wheelTrack": "1.491",
               "cargoVolume": "583",
               "fuel": "Gasoline"
            },
            {
               "fullName": "HONDA Jazz/Fit",
               "firstYearProduction": "2004",
               "lastYearProduction": "2008",
               "topSpeed": "170",
               "acceleration": "13.7",
               "drive type": "Front Wheel Drive",
               "gearBox": "5-manual speed",
               "length": "3840",
               "width": "1679",
               "height": "1519",
               "wheelBase": "2451",
               "wheelTrack": "1.461",
               "cargoVolume": "379",
               "fuel": "Gasoline"
            },
            {
               "fullName": "HONDA Jazz/Fit",
               "firstYearProduction": "2002",
               "lastYearProduction": "2004",
               "topSpeed": "167",
               "acceleration": "13.1",
               "drive type": "Front Wheel Drive",
               "gearBox": "5-Speed manual",
               "length": "3830",
               "width": "1679",
               "height": "1519",
               "wheelBase": "2451",
               "wheelTrack": "1.461",
               "cargoVolume": "379",
               "fuel": "Gasoline"
            }
         ]
      },
      {
         "modelName": "HONDA Accord",
         "firstYearProduction": "1981",
         "engineType": "Gasoline, Hybrid gasoline, Hybrid, Diesel",
         "generations": [
            {
               "fullName": "HONDA Accord",
               "firstYearProduction": "2020",
               "lastYearProduction": "Present",
               "drive type": "Front Wheel Drive",
               "gearBox": "CVT Automatic",
               "fuel": "Gasoline"
            },
            {
               "fullName": "HONDA Accord",
               "firstYearProduction": "2017",
               "lastYearProduction": "2020",
               "drive type": "Front Wheel Drive",
               "gearBox": "6-speed manual",
               "length": "4882",
               "width": "1862",
               "height": "1450",
               "wheelBase": "2830",
               "wheelTrack": "1.600",
               "cargoVolume": "473",
               "fuel": "Gasoline"
            },
            {
               "fullName": "HONDA Accord",
               "firstYearProduction": "2015",
               "lastYearProduction": "2017",
               "drive type": "Front Wheel Drive",
               "gearBox": "6-speed manual",
               "length": "4890",
               "width": "1849",
               "height": "1466",
               "wheelBase": "2776",
               "wheelTrack": "1.595",
               "cargoVolume": "447",
               "fuel": "Gasoline"
            },
            {
               "fullName": "HONDA Accord",
               "firstYearProduction": "2012",
               "lastYearProduction": "2015",
               "topSpeed": "209",
               "drive type": "Front Wheel Drive",
               "gearBox": "6-speed manual",
               "length": "4862",
               "width": "1849",
               "height": "1466",
               "wheelBase": "2776",
               "wheelTrack": "1.585",
               "cargoVolume": "447",
               "fuel": "Gasoline"
            },
            {
               "fullName": "HONDA Accord Sedan US",
               "firstYearProduction": "2008",
               "lastYearProduction": "2012",
               "topSpeed": "225",
               "acceleration": "7.6",
               "drive type": "Front Wheel Drive",
               "gearBox": "5-speed automatic",
               "length": "4930",
               "width": "1847",
               "height": "1476",
               "wheelBase": "2799",
               "wheelTrack": "1.590",
               "cargoVolume": "396",
               "fuel": "Gasoline"
            },
            {
               "fullName": "HONDA Accord Sedan US",
               "firstYearProduction": "2005",
               "lastYearProduction": "2007",
               "topSpeed": "233",
               "acceleration": "8",
               "drive type": "Front Wheel Drive",
               "gearBox": "5-speed manual",
               "length": "4854",
               "width": "1819",
               "height": "1453",
               "wheelBase": "2741",
               "wheelTrack": "1.552",
               "cargoVolume": "396",
               "fuel": "Gasoline"
            },
            {
               "fullName": "HONDA Accord Sedan US",
               "firstYearProduction": "2002",
               "lastYearProduction": "2005",
               "topSpeed": "200",
               "acceleration": "9.3",
               "drive type": "Front Wheel Drive",
               "gearBox": "5-speed manual",
               "length": "4813",
               "width": "1816",
               "height": "1450",
               "wheelBase": "2741",
               "wheelTrack": "1.552",
               "cargoVolume": "396",
               "fuel": "Gasoline"
            },
            {
               "fullName": "HONDA Accord Sedan US",
               "firstYearProduction": "1997",
               "lastYearProduction": "2002",
               "topSpeed": "196",
               "acceleration": "10.3",
               "drive type": "Front Wheel Drive",
               "gearBox": "5-speed manual",
               "length": "4796",
               "width": "1786",
               "height": "1445",
               "wheelBase": "2715",
               "wheelTrack": "1.554",
               "cargoVolume": "396",
               "fuel": "Gasoline"
            },
            {
               "fullName": "HONDA Accord 4 Doors",
               "firstYearProduction": "1996",
               "lastYearProduction": "1998",
               "topSpeed": "195",
               "acceleration": "12.5",
               "drive type": "Front Wheel Drive",
               "gearBox": "4-speed automatic",
               "length": "4681",
               "width": "1720",
               "height": "1379",
               "wheelBase": "2720",
               "wheelTrack": "1.481",
               "cargoVolume": "405",
               "fuel": "Gasoline"
            },
            {
               "fullName": "HONDA Accord 4 Doors",
               "firstYearProduction": "1993",
               "lastYearProduction": "1996",
               "topSpeed": "200",
               "acceleration": "10.2",
               "drive type": "Front Wheel Drive",
               "gearBox": "5-speed manual",
               "length": "4676",
               "width": "1720",
               "height": "1379",
               "wheelBase": "2720",
               "wheelTrack": "1.476",
               "cargoVolume": "405",
               "fuel": "Gasoline"
            },
            {
               "fullName": "HONDA Accord 4 Doors",
               "firstYearProduction": "1989",
               "lastYearProduction": "1993",
               "topSpeed": "180",
               "acceleration": "13.5",
               "drive type": "Front Wheel Drive",
               "gearBox": "4-speed automatic",
               "length": "4699",
               "width": "1699",
               "height": "1389",
               "wheelBase": "2720",
               "wheelTrack": "1.481",
               "cargoVolume": "439",
               "fuel": "Gasoline"
            },
            {
               "fullName": "HONDA Accord 4 Doors",
               "firstYearProduction": "1981",
               "lastYearProduction": "1985",
               "topSpeed": "163",
               "acceleration": "16.3",
               "drive type": "Front Wheel Drive",
               "gearBox": "3-speed automatic",
               "length": "4409",
               "width": "1651",
               "height": "1374",
               "wheelBase": "2380",
               "wheelTrack": "1.430",
               "cargoVolume": "419",
               "fuel": "Gasoline"
            }
         ]
      },
      {
         "modelName": "HONDA Ridgeline",
         "firstYearProduction": "2005",
         "engineType": ", Gasoline",
         "style": "Truck",
         "generations": [
            {
               "fullName": "HONDA Ridgeline",
               "firstYearProduction": "2021",
               "lastYearProduction": "Present"
            },
            {
               "fullName": "HONDA Ridgeline",
               "firstYearProduction": "2016",
               "lastYearProduction": "2020",
               "drive type": "Rear Wheel Drive",
               "gearBox": "6-speed automatic",
               "length": "5334",
               "width": "1996",
               "height": "1783",
               "wheelBase": "3180",
               "cargoVolume": "960",
               "fuel": "Gasoline"
            },
            {
               "fullName": "HONDA Ridgeline",
               "firstYearProduction": "2009",
               "lastYearProduction": "2014",
               "topSpeed": "177",
               "acceleration": "9.3",
               "drive type": "All Wheel Drive",
               "gearBox": "5-speed automatic",
               "length": "5258",
               "width": "1976",
               "height": "1786",
               "wheelBase": "3099",
               "wheelTrack": "1.704",
               "cargoVolume": "241",
               "fuel": "Gasoline"
            },
            {
               "fullName": "HONDA Ridgeline",
               "firstYearProduction": "2005",
               "lastYearProduction": "2009",
               "drive type": "All Wheel Drive",
               "gearBox": "5-Speed manual",
               "length": "5253",
               "width": "1938",
               "height": "1786",
               "wheelBase": "3099",
               "wheelTrack": "1.704",
               "fuel": "Gasoline"
            }
         ]
      },
      {
         "modelName": "HONDA Odyssey",
         "firstYearProduction": "2005",
         "engineType": "Gasoline",
         "style": "Van",
         "generations": [
            {
               "fullName": "HONDA Odyssey",
               "firstYearProduction": "2020",
               "lastYearProduction": "Present",
               "drive type": "Front Wheel Drive",
               "gearBox": "10-Speed automatic",
               "length": "5161",
               "width": "1994",
               "height": "1735",
               "wheelBase": "3000",
               "wheelTrack": "1.735",
               "cargoVolume": "929",
               "fuel": "Gasoline"
            },
            {
               "fullName": "HONDA Odyssey",
               "firstYearProduction": "2017",
               "lastYearProduction": "2020",
               "drive type": "Front Wheel Drive",
               "gearBox": "10-Speed automatic",
               "length": "5161",
               "width": "1994",
               "height": "1735",
               "wheelBase": "3000",
               "wheelTrack": "1.709",
               "cargoVolume": "929",
               "fuel": "Gasoline"
            },
            {
               "fullName": "HONDA Odyssey",
               "firstYearProduction": "2011",
               "lastYearProduction": "2017",
               "drive type": "Front Wheel Drive",
               "gearBox": "5-speed automatic",
               "length": "5154",
               "width": "2012",
               "height": "1737",
               "wheelBase": "3000",
               "wheelTrack": "1.730",
               "cargoVolume": "2636",
               "fuel": "Gasoline"
            },
            {
               "fullName": "HONDA Odyssey",
               "firstYearProduction": "2008",
               "lastYearProduction": "2011",
               "drive type": "Front Wheel Drive",
               "gearBox": "5-speed automatic",
               "length": "5105",
               "width": "1958",
               "height": "1778",
               "wheelBase": "3000",
               "wheelTrack": "1.694",
               "cargoVolume": "2580",
               "fuel": "Gasoline"
            },
            {
               "fullName": "HONDA Odyssey",
               "firstYearProduction": "2005",
               "lastYearProduction": "2008",
               "drive type": "Front Wheel Drive",
               "gearBox": "5-speed automatic",
               "length": "5105",
               "width": "1958",
               "height": "1778",
               "wheelBase": "3000",
               "wheelTrack": "1.694",
               "cargoVolume": "2580",
               "fuel": "Gasoline"
            }
         ]
      },
      {
         "modelName": "HONDA CR-V",
         "firstYearProduction": "1996",
         "engineType": "Gasoline, Hybrid, Diesel",
         "style": "SUV (Sports Utility Vehicle)",
         "generations": [
            {
               "fullName": "HONDA CR-V",
               "firstYearProduction": "2019",
               "lastYearProduction": "Present",
               "topSpeed": "180",
               "acceleration": "8.8",
               "drive type": "Front Wheel Drive",
               "gearBox": "CVT",
               "length": "4587",
               "width": "1854",
               "height": "1679",
               "wheelBase": "2659",
               "wheelTrack": "1.600",
               "cargoVolume": "498",
               "fuel": "Gasoline"
            },
            {
               "fullName": "HONDA CR-V",
               "firstYearProduction": "2016",
               "lastYearProduction": "2019",
               "topSpeed": "182",
               "acceleration": "12.3",
               "drive type": "Front Wheel Drive",
               "gearBox": "CVT",
               "length": "4587",
               "width": "1854",
               "height": "1679",
               "wheelBase": "2659",
               "wheelTrack": "1.600",
               "cargoVolume": "589",
               "fuel": "Gasoline"
            },
            {
               "fullName": "HONDA CR-V",
               "firstYearProduction": "2014",
               "lastYearProduction": "2016",
               "topSpeed": "182",
               "acceleration": "12.3",
               "drive type": "All Wheel Drive",
               "gearBox": "5-speed automatic",
               "length": "4529",
               "width": "1819",
               "height": "1643",
               "wheelBase": "2619",
               "wheelTrack": "1.577",
               "cargoVolume": "589",
               "fuel": "Gasoline"
            },
            {
               "fullName": "HONDA HONDA CR-V",
               "firstYearProduction": "2011",
               "lastYearProduction": "2014",
               "topSpeed": "190",
               "acceleration": "10",
               "drive type": "Front Wheel Drive",
               "gearBox": "6 speed manual",
               "length": "4529",
               "width": "1819",
               "height": "1654",
               "wheelBase": "2619",
               "wheelTrack": "1.570",
               "cargoVolume": "589",
               "fuel": "Gasoline"
            },
            {
               "fullName": "HONDA CR-V",
               "firstYearProduction": "2010",
               "lastYearProduction": "2011",
               "topSpeed": "177",
               "acceleration": "12.2",
               "drive type": "All Wheel Drive",
               "gearBox": "5-speed automatic",
               "length": "4529",
               "width": "1819",
               "height": "1676",
               "wheelBase": "2629",
               "wheelTrack": "1.565",
               "cargoVolume": "555",
               "fuel": "Gasoline"
            },
            {
               "fullName": "HONDA CR-V",
               "firstYearProduction": "2007",
               "lastYearProduction": "2009",
               "topSpeed": "177",
               "acceleration": "12.2",
               "drive type": "All Wheel Drive",
               "gearBox": "5-speed automatic",
               "length": "4529",
               "width": "1821",
               "height": "1811",
               "wheelBase": "2619",
               "wheelTrack": "1.565",
               "cargoVolume": "524",
               "fuel": "Gasoline"
            },
            {
               "fullName": "HONDA CR-V",
               "firstYearProduction": "2004",
               "lastYearProduction": "2007",
               "topSpeed": "167",
               "acceleration": "12",
               "drive type": "All Wheel Drive",
               "gearBox": "4-speed automatic",
               "length": "4641",
               "width": "1781",
               "height": "1709",
               "wheelBase": "2629",
               "wheelTrack": "1.539",
               "cargoVolume": "527",
               "fuel": "Gasoline"
            },
            {
               "fullName": "HONDA CR-V",
               "firstYearProduction": "2002",
               "lastYearProduction": "2004",
               "topSpeed": "167",
               "acceleration": "12",
               "drive type": "All Wheel Drive",
               "gearBox": "4-speed automatic",
               "length": "4559",
               "width": "1781",
               "height": "1709",
               "wheelBase": "2629",
               "wheelTrack": "1.539",
               "cargoVolume": "527",
               "fuel": "Gasoline"
            },
            {
               "fullName": "HONDA CR-V",
               "firstYearProduction": "1996",
               "lastYearProduction": "2001",
               "topSpeed": "166",
               "acceleration": "12.5",
               "drive type": "Front Wheel Drive",
               "gearBox": "4-speed automatic",
               "length": "4491",
               "width": "1750",
               "height": "1704",
               "wheelBase": "2619",
               "wheelTrack": "1.534",
               "cargoVolume": "665",
               "fuel": "Gasoline"
            }
         ]
      },
      {
         "modelName": "HONDA Pilot",
         "firstYearProduction": "2009",
         "engineType": "Gasoline",
         "style": "SUV (Sports Utility Vehicle)",
         "generations": [
            {
               "fullName": "HONDA Pilot",
               "firstYearProduction": "2018",
               "lastYearProduction": "Present",
               "drive type": "Rear Wheel Drive",
               "gearBox": "6-speed automatic",
               "length": "4940",
               "width": "1996",
               "height": "1773",
               "wheelBase": "2819",
               "wheelTrack": "1.684",
               "cargoVolume": "467",
               "fuel": "Gasoline"
            },
            {
               "fullName": "HONDA Pilot",
               "firstYearProduction": "2016",
               "lastYearProduction": "2018",
               "drive type": "All Wheel Drive",
               "gearBox": "6-speed automatic",
               "length": "4940",
               "width": "1996",
               "height": "1773",
               "wheelBase": "2819",
               "wheelTrack": "1.684",
               "cargoVolume": "467",
               "fuel": "Gasoline"
            },
            {
               "fullName": "HONDA Pilot",
               "firstYearProduction": "2009",
               "lastYearProduction": "2016",
               "topSpeed": "180",
               "acceleration": "9.9",
               "drive type": "All Wheel Drive",
               "gearBox": "5-speed automatic",
               "length": "4849",
               "width": "1994",
               "height": "1803",
               "wheelBase": "2774",
               "wheelTrack": "1.720",
               "cargoVolume": "510",
               "fuel": "Gasoline"
            }
         ]
      },
      {
         "modelName": "HONDA Civic Coupe",
         "firstYearProduction": "1994",
         "engineType": "Gasoline",
         "style": "Coup\u00e9 (two-door)",
         "generations": [
            {
               "fullName": "HONDA Civic Coupe",
               "firstYearProduction": "2018",
               "lastYearProduction": "Present",
               "drive type": "Front Wheel Drive",
               "gearBox": "CVT",
               "length": "4493",
               "width": "1798",
               "height": "1394",
               "wheelBase": "2700",
               "wheelTrack": "1.547",
               "cargoVolume": "337",
               "fuel": "Gasoline"
            },
            {
               "fullName": "HONDA Civic Coupe",
               "firstYearProduction": "2016",
               "lastYearProduction": "2018",
               "drive type": "Front Wheel Drive",
               "gearBox": "6-speed manual",
               "length": "4493",
               "width": "1798",
               "height": "1394",
               "wheelBase": "2700",
               "wheelTrack": "1.547",
               "cargoVolume": "337",
               "fuel": "Gasoline"
            },
            {
               "fullName": "HONDA Civic Si Coupe",
               "firstYearProduction": "2015",
               "lastYearProduction": "2016",
               "drive type": "Front Wheel Drive",
               "gearBox": "6-speed manual",
               "length": "4542",
               "width": "1753",
               "height": "1397",
               "wheelBase": "2621",
               "wheelTrack": "1.504",
               "cargoVolume": "331",
               "fuel": "Gasoline"
            },
            {
               "fullName": "HONDA Civic Coupe",
               "firstYearProduction": "2015",
               "lastYearProduction": "2016",
               "drive type": "Front Wheel Drive",
               "gearBox": "5-speed manual",
               "length": "4519",
               "width": "1753",
               "height": "1397",
               "wheelBase": "3307",
               "wheelTrack": "1.499",
               "cargoVolume": "331",
               "fuel": "Gasoline"
            },
            {
               "fullName": "HONDA Civic Coupe",
               "firstYearProduction": "2012",
               "lastYearProduction": "2015",
               "drive type": "Front Wheel Drive",
               "gearBox": "5-Speed manual",
               "length": "4458",
               "width": "1753",
               "height": "1397",
               "wheelBase": "2621",
               "wheelTrack": "1.499",
               "cargoVolume": "328",
               "fuel": "Gasoline"
            },
            {
               "fullName": "HONDA Civic Coupe Si",
               "firstYearProduction": "2012",
               "lastYearProduction": "2015",
               "topSpeed": "201",
               "acceleration": "6.7",
               "drive type": "Front Wheel Drive",
               "gearBox": "6-Speed manual",
               "length": "4473",
               "width": "1753",
               "height": "1397",
               "wheelBase": "2619",
               "wheelTrack": "1.499",
               "cargoVolume": "331",
               "fuel": "Gasoline"
            },
            {
               "fullName": "HONDA Civic Coupe",
               "firstYearProduction": "2008",
               "lastYearProduction": "2011",
               "topSpeed": "204",
               "acceleration": "9.2",
               "drive type": "Front Wheel Drive",
               "gearBox": "5-speed manual",
               "length": "4458",
               "width": "1750",
               "height": "1397",
               "wheelBase": "2649",
               "wheelTrack": "1.499",
               "cargoVolume": "326",
               "fuel": "Gasoline"
            },
            {
               "fullName": "HONDA Civic Coupe Si",
               "firstYearProduction": "2008",
               "lastYearProduction": "2011",
               "topSpeed": "212",
               "acceleration": "7",
               "drive type": "Front Wheel Drive",
               "gearBox": "6-speed manual",
               "length": "4440",
               "width": "1750",
               "height": "1359",
               "wheelBase": "2649",
               "wheelTrack": "1.499",
               "cargoVolume": "326",
               "fuel": "Gasoline"
            },
            {
               "fullName": "HONDA Civic Coupe Si",
               "firstYearProduction": "2006",
               "lastYearProduction": "2008",
               "topSpeed": "240",
               "acceleration": "7.1",
               "drive type": "Front Wheel Drive",
               "gearBox": "6-speed manual",
               "length": "4440",
               "width": "1750",
               "height": "1359",
               "wheelBase": "2649",
               "wheelTrack": "1.499",
               "cargoVolume": "326",
               "fuel": "Gasoline"
            },
            {
               "fullName": "HONDA Civic Coupe",
               "firstYearProduction": "2005",
               "lastYearProduction": "2008",
               "topSpeed": "240",
               "acceleration": "7.1",
               "drive type": "Front Wheel Drive",
               "gearBox": "5-speed manual",
               "length": "4440",
               "width": "1750",
               "height": "1359",
               "wheelBase": "2649",
               "wheelTrack": "1.499",
               "cargoVolume": "326",
               "fuel": "Gasoline"
            },
            {
               "fullName": "HONDA Civic Coupe",
               "firstYearProduction": "2001",
               "lastYearProduction": "2005",
               "topSpeed": "200",
               "acceleration": "9.7",
               "drive type": "Front Wheel Drive",
               "gearBox": "4-Speed automatic",
               "length": "4440",
               "width": "1699",
               "height": "1400",
               "wheelBase": "2619",
               "wheelTrack": "1.471",
               "cargoVolume": "442",
               "fuel": "Gasoline"
            },
            {
               "fullName": "HONDA Civic Coupe",
               "firstYearProduction": "1996",
               "lastYearProduction": "2001",
               "topSpeed": "190",
               "acceleration": "10.1",
               "drive type": "Front Wheel Drive",
               "gearBox": "4-Speed automatic",
               "length": "4460",
               "width": "1699",
               "height": "1379",
               "wheelBase": "2619",
               "wheelTrack": "1.481",
               "cargoVolume": "405",
               "fuel": "Gasoline"
            },
            {
               "fullName": "HONDA Civic Coupe",
               "firstYearProduction": "1994",
               "lastYearProduction": "1996",
               "topSpeed": "190",
               "acceleration": "9.9",
               "drive type": "Front Wheel Drive",
               "gearBox": "5-Speed manual",
               "length": "4399",
               "width": "1699",
               "height": "1341",
               "wheelBase": "2619",
               "wheelTrack": "1.481",
               "cargoVolume": "365",
               "fuel": "Gasoline"
            }
         ]
      },
      {
         "modelName": "HONDA Civic Type-R",
         "firstYearProduction": "2001",
         "engineType": "Gasoline",
         "style": "Hatchback",
         "generations": [
            {
               "fullName": "HONDA Civic Type-R",
               "firstYearProduction": "2017",
               "lastYearProduction": "Present",
               "topSpeed": "272",
               "acceleration": "5.7",
               "drive type": "Front Wheel Drive",
               "gearBox": "6-speed manual",
               "length": "4557",
               "width": "1877",
               "height": "1435",
               "wheelBase": "2700",
               "wheelTrack": "1.600",
               "cargoVolume": "419",
               "fuel": "Gasoline"
            },
            {
               "fullName": "HONDA Civic Type-R",
               "firstYearProduction": "2015",
               "lastYearProduction": "2016",
               "topSpeed": "270",
               "acceleration": "5.7",
               "drive type": "Front Wheel Drive",
               "gearBox": "6-speed manual",
               "length": "4389",
               "width": "1877",
               "height": "1466",
               "wheelBase": "2593",
               "wheelTrack": "1.605",
               "cargoVolume": "498",
               "fuel": "Gasoline"
            },
            {
               "fullName": "HONDA Civic Type-R Mugen",
               "firstYearProduction": "2009",
               "lastYearProduction": "2010",
               "topSpeed": "241",
               "acceleration": "6",
               "drive type": "Front Wheel Drive",
               "gearBox": "6-speed manual",
               "length": "4280",
               "width": "1793",
               "height": "1440",
               "wheelBase": "2634",
               "wheelTrack": "1.506",
               "cargoVolume": "484",
               "fuel": "Gasoline"
            },
            {
               "fullName": "HONDA Civic Type-R",
               "firstYearProduction": "2008",
               "lastYearProduction": "2010",
               "topSpeed": "235",
               "acceleration": "6.6",
               "drive type": "Front Wheel Drive",
               "gearBox": "6-speed manual",
               "length": "4275",
               "width": "1786",
               "height": "1445",
               "wheelBase": "2634",
               "wheelTrack": "1.506",
               "cargoVolume": "484",
               "fuel": "Gasoline"
            },
            {
               "fullName": "HONDA Civic Type-R",
               "firstYearProduction": "2006",
               "lastYearProduction": "2007",
               "topSpeed": "235",
               "acceleration": "6.6",
               "drive type": "Front Wheel Drive",
               "gearBox": "6-Speed manual",
               "length": "4140",
               "width": "1699",
               "height": "1420",
               "wheelBase": "2581",
               "wheelTrack": "1.471",
               "fuel": "Gasoline"
            },
            {
               "fullName": "HONDA Civic Type-R",
               "firstYearProduction": "2001",
               "lastYearProduction": "2005",
               "topSpeed": "235",
               "acceleration": "6.8",
               "drive type": "Front Wheel Drive",
               "gearBox": "6-Speed manual",
               "length": "4140",
               "width": "1699",
               "height": "1420",
               "wheelBase": "2581",
               "wheelTrack": "1.471",
               "cargoVolume": "314",
               "fuel": "Gasoline"
            }
         ]
      },
      {
         "modelName": "HONDA Insight",
         "firstYearProduction": "1999",
         "engineType": "Hybrid, Hybrid gasoline, Gasoline",
         "style": "Hatchback",
         "generations": [
            {
               "fullName": "HONDA Insight",
               "firstYearProduction": "2018",
               "lastYearProduction": "Present",
               "drive type": "Front Wheel Drive",
               "gearBox": "CVT",
               "length": "4663",
               "width": "1819",
               "height": "1412",
               "wheelBase": "2700",
               "wheelTrack": "61",
               "cargoVolume": "428",
               "fuel": "Hybrid"
            },
            {
               "fullName": "HONDA insight",
               "firstYearProduction": "2012",
               "lastYearProduction": "2014",
               "topSpeed": "182",
               "acceleration": "12.5",
               "drive type": "Front Wheel Drive",
               "gearBox": "CVT",
               "length": "4394",
               "width": "1694",
               "height": "1425",
               "wheelBase": "2545",
               "wheelTrack": "1.496",
               "cargoVolume": "340",
               "fuel": "Hybrid Gasoline"
            },
            {
               "fullName": "HONDA Insight",
               "firstYearProduction": "2009",
               "lastYearProduction": "2012",
               "topSpeed": "182",
               "acceleration": "12.4",
               "drive type": "Front Wheel Drive",
               "gearBox": "Continuously Variable Transmission (CVT)",
               "length": "4376",
               "width": "1694",
               "height": "1427",
               "wheelBase": "2550",
               "wheelTrack": "1.491",
               "cargoVolume": "450",
               "fuel": "Gasoline"
            },
            {
               "fullName": "HONDA Insight",
               "firstYearProduction": "1999",
               "lastYearProduction": "2006",
               "topSpeed": "180",
               "acceleration": "12",
               "drive type": "Front Wheel Drive",
               "gearBox": "5-Speed manual",
               "length": "3945",
               "width": "1694",
               "height": "1354",
               "wheelBase": "2400",
               "wheelTrack": "1.435",
               "cargoVolume": "139",
               "fuel": "Hybrid"
            }
         ]
      },
      {
         "modelName": "HONDA Legend Sedan",
         "firstYearProduction": "1987",
         "engineType": "Hybrid, Gasoline",
         "generations": [
            {
               "fullName": "HONDA Legend",
               "firstYearProduction": "2014",
               "lastYearProduction": "Present",
               "topSpeed": "249",
               "acceleration": "5.2",
               "drive type": "All Wheel Drive",
               "gearBox": "7-speed automatic",
               "length": "4981",
               "width": "1890",
               "height": "1466",
               "wheelBase": "2850",
               "wheelTrack": "1.633",
               "fuel": "Hybrid"
            },
            {
               "fullName": "HONDA Legend",
               "firstYearProduction": "2009",
               "lastYearProduction": "2012",
               "topSpeed": "249",
               "acceleration": "7.1",
               "drive type": "All Wheel Drive",
               "gearBox": "5-speed automatic",
               "length": "4986",
               "width": "1844",
               "height": "1455",
               "wheelBase": "2799",
               "wheelTrack": "1.575",
               "cargoVolume": "453",
               "fuel": "Gasoline"
            },
            {
               "fullName": "HONDA Legend Sedan",
               "firstYearProduction": "2004",
               "lastYearProduction": "2008",
               "topSpeed": "250",
               "acceleration": "7.3",
               "drive type": "All Wheel Drive",
               "gearBox": "6-speed automatic",
               "length": "4917",
               "width": "1847",
               "height": "1453",
               "wheelBase": "2799",
               "wheelTrack": "1.575",
               "cargoVolume": "447",
               "fuel": "Gasoline"
            },
            {
               "fullName": "HONDA Legend Sedan",
               "firstYearProduction": "1996",
               "lastYearProduction": "2005",
               "topSpeed": "215",
               "acceleration": "9.1",
               "drive type": "Front Wheel Drive",
               "gearBox": "4-Speed automatic",
               "length": "4981",
               "width": "1811",
               "height": "1430",
               "wheelBase": "2901",
               "wheelTrack": "1.560",
               "cargoVolume": "450",
               "fuel": "Gasoline"
            },
            {
               "fullName": "HONDA Legend Sedan",
               "firstYearProduction": "1991",
               "lastYearProduction": "1996",
               "topSpeed": "223",
               "acceleration": "8.1",
               "drive type": "Front Wheel Drive",
               "gearBox": "4-Speed automatic",
               "length": "4950",
               "width": "1811",
               "height": "1410",
               "wheelBase": "2911",
               "wheelTrack": "1.549",
               "cargoVolume": "428",
               "fuel": "Gasoline"
            },
            {
               "fullName": "HONDA Legend Sedan",
               "firstYearProduction": "1987",
               "lastYearProduction": "1991",
               "topSpeed": "210",
               "acceleration": "8",
               "drive type": "Front Wheel Drive",
               "gearBox": "4-Speed automatic",
               "length": "4811",
               "width": "1740",
               "height": "1389",
               "wheelBase": "2761",
               "wheelTrack": "1.491",
               "cargoVolume": "470",
               "fuel": "Gasoline"
            }
         ]
      },
      {
         "modelName": "HONDA Civic Sedan US",
         "firstYearProduction": "2005",
         "engineType": "Hybrid, Gasoline",
         "generations": [
            {
               "fullName": "HONDA Civic Sedan US",
               "firstYearProduction": "2008",
               "lastYearProduction": "Present",
               "topSpeed": "185",
               "acceleration": "12.4",
               "drive type": "Front Wheel Drive",
               "gearBox": "5-speed automatic",
               "length": "4503",
               "width": "1753",
               "height": "1435",
               "wheelBase": "2700",
               "wheelTrack": "1.499",
               "cargoVolume": "340",
               "fuel": "Gasoline"
            },
            {
               "fullName": "HONDA Civic Sedan Si US",
               "firstYearProduction": "2008",
               "lastYearProduction": "Present",
               "topSpeed": "212",
               "acceleration": "7",
               "drive type": "Front Wheel Drive",
               "gearBox": "6-speed manual",
               "length": "4503",
               "width": "1753",
               "height": "1435",
               "wheelBase": "2700",
               "wheelTrack": "1.499",
               "cargoVolume": "340",
               "fuel": "Gasoline"
            },
            {
               "fullName": "HONDA Civic Sedan Si US",
               "firstYearProduction": "2007",
               "lastYearProduction": "2008",
               "topSpeed": "212",
               "acceleration": "7",
               "drive type": "Front Wheel Drive",
               "gearBox": "6-speed manual",
               "length": "4488",
               "width": "1753",
               "height": "1435",
               "wheelBase": "2700",
               "wheelTrack": "1.499",
               "cargoVolume": "340",
               "fuel": "Gasoline"
            },
            {
               "fullName": "HONDA Civic Sedan US",
               "firstYearProduction": "2005",
               "lastYearProduction": "2008",
               "topSpeed": "185",
               "acceleration": "12.5",
               "drive type": "Front Wheel Drive",
               "gearBox": "5-speed manual",
               "length": "4488",
               "width": "1753",
               "height": "1435",
               "wheelBase": "2700",
               "wheelTrack": "1.499",
               "cargoVolume": "340",
               "fuel": "Gasoline"
            }
         ]
      },
      {
         "modelName": "HONDA NSX",
         "firstYearProduction": "1991",
         "engineType": "Hybrid, Gasoline",
         "style": "Coup\u00e9 (two-door)",
         "generations": [
            {
               "fullName": "HONDA NSX",
               "firstYearProduction": "2016",
               "lastYearProduction": "Present",
               "topSpeed": "306",
               "acceleration": "3.8",
               "drive type": "All Wheel Drive",
               "gearBox": "9-speed automatic (DCT)",
               "length": "4470",
               "width": "1941",
               "height": "1214",
               "wheelBase": "2629",
               "wheelTrack": "1.656",
               "cargoVolume": "125",
               "fuel": "Hybrid"
            },
            {
               "fullName": "HONDA NSX",
               "firstYearProduction": "2002",
               "lastYearProduction": "2005",
               "topSpeed": "261",
               "acceleration": "7.5",
               "drive type": "Rear Wheel Drive",
               "gearBox": "4-speed automatic",
               "length": "4420",
               "width": "1811",
               "height": "1171",
               "wheelBase": "2530",
               "wheelTrack": "1.509",
               "cargoVolume": "153",
               "fuel": "Gasoline"
            },
            {
               "fullName": "HONDA NSX",
               "firstYearProduction": "1997",
               "lastYearProduction": "2002",
               "topSpeed": "261",
               "acceleration": "6.9",
               "drive type": "Rear Wheel Drive",
               "gearBox": "4-speed automatic",
               "length": "4420",
               "width": "1811",
               "height": "1181",
               "wheelBase": "2530",
               "wheelTrack": "1.509",
               "cargoVolume": "153",
               "fuel": "Gasoline"
            },
            {
               "fullName": "HONDA NSX",
               "firstYearProduction": "1991",
               "lastYearProduction": "1997",
               "topSpeed": "261",
               "acceleration": "6.9",
               "drive type": "Rear Wheel Drive",
               "gearBox": "4-speed automatic",
               "length": "4420",
               "width": "1811",
               "height": "1181",
               "wheelBase": "2530",
               "wheelTrack": "1.509",
               "cargoVolume": "153",
               "fuel": "Gasoline"
            }
         ]
      },
      {
         "modelName": "HONDA e",
         "firstYearProduction": "2020",
         "engineType": "Electric",
         "style": "Hatchback",
         "generations": [
            {
               "fullName": "HONDA e",
               "firstYearProduction": "2020",
               "lastYearProduction": "Present",
               "topSpeed": "150",
               "acceleration": "8",
               "drive type": "Front Wheel Drive",
               "gearBox": "1-Speed automatic",
               "length": "3894",
               "width": "1750",
               "height": "1496",
               "wheelBase": "2499",
               "wheelTrack": "1.519",
               "cargoVolume": "170",
               "fuel": "Electric"
            }
         ]
      },
      {
         "modelName": "HONDA Passport",
         "firstYearProduction": "2018",
         "engineType": "Gasoline",
         "style": "SUV (Sports Utility Vehicle)",
         "generations": [
            {
               "fullName": "HONDA Passport",
               "firstYearProduction": "2018",
               "lastYearProduction": "Present",
               "drive type": "Front Wheel Drive",
               "gearBox": "9-Speed automatic ",
               "length": "4839",
               "width": "1996",
               "height": "1819",
               "wheelBase": "2819",
               "wheelTrack": "1.702",
               "cargoVolume": "1167",
               "fuel": "Gasoline"
            }
         ]
      },
      {
         "modelName": "HONDA S660",
         "firstYearProduction": "2015",
         "engineType": "Gasoline",
         "style": "Convertible (spider/spyder, cabrio/cabriolet, drop/open/soft top)",
         "generations": [
            {
               "fullName": "HONDA S660",
               "firstYearProduction": "2015",
               "lastYearProduction": "Present",
               "drive type": "Rear Wheel Drive",
               "gearBox": "6-speed manual",
               "length": "3396",
               "width": "1476",
               "height": "1181",
               "wheelBase": "2286",
               "fuel": "Gasoline"
            }
         ]
      }
   ]
}